tmsgit/__init__.py
tmsgit/__main__.py
tmsgit/commands.py
tmsgit-0.0.3.dist-info/METADATA
tmsgit-0.0.3.dist-info/WHEEL
tmsgit-0.0.3.dist-info/entry_points.txt
tmsgit-0.0.3.dist-info/top_level.txt
tmsgit-0.0.3.dist-info/RECORD
